goose/__init__.py
goose/errors.py
goose/flow.py
goose/py.typed
goose/runs.py
goose/task.py
goose/_internal/agent.py
goose/_internal/conversation.py
goose/_internal/flow.py
goose/_internal/result.py
goose/_internal/state.py
goose/_internal/store.py
goose/_internal/task.py
goose/_internal/types/__init__.py
goose/_internal/types/telemetry.py
goose_py-0.12.0.dist-info/METADATA
goose_py-0.12.0.dist-info/WHEEL
goose_py-0.12.0.dist-info/RECORD
