Metadata-Version: 2.4
Name: goose-py
Version: 0.12.0
Summary: A tool for AI workflows based on human-computer collaboration and structured output.
Author-email: Nash Taylor <nash@chelle.ai>, Joshua Cook <joshua@chelle.ai>, Michael Sankur <michael@chelle.ai>
Requires-Python: >=3.12
Requires-Dist: aikernel==0.1.43
Requires-Dist: jsonpath-ng>=1.7.0
Requires-Dist: pydantic>=2.8.2
